{
  "meta": {
    "sample_id": "game_2025-06-02b_move_066",
    "game_name": "2025-06-02b",
    "event": "51st Tengen",
    "date": "2025-06-02",
    "black_player": "Yu Zhengqi",
    "white_player": "Fujisawa Rina"
  },
  "rules": {
    "board_size": 19,
    "komi": 6.5,
    "result": "B+R"
  },
  "state": {
    "move_number": 66,
    "to_play": 1,
    "last_move": {
      "color": 0,
      "point": "T17"
    },
    "recent_moves": [
      {
        "color": 1,
        "point": "T16"
      },
      {
        "color": 0,
        "point": "S15"
      },
      {
        "color": 1,
        "point": "S17"
      },
      {
        "color": 0,
        "point": "S16"
      },
      {
        "color": 1,
        "point": "T18"
      },
      {
        "color": 0,
        "point": "T17"
      }
    ],
    "black_stones": [
      "K2",
      "C3",
      "J3",
      "Q3",
      "B4",
      "K4",
      "O4",
      "P4",
      "R4",
      "B5",
      "K5",
      "N5",
      "B6",
      "C6",
      "K6",
      "L6",
      "M6",
      "N6",
      "D7",
      "F8",
      "R12",
      "S12",
      "R13",
      "R14",
      "Q15",
      "Q16",
      "T16",
      "Q17",
      "Q18",
      "R18",
      "T18"
    ],
    "white_stones": [
      "P2",
      "F3",
      "K3",
      "L3",
      "M3",
      "N3",
      "D4",
      "L4",
      "N4",
      "C5",
      "L5",
      "M5",
      "O5",
      "D6",
      "E6",
      "C7",
      "C8",
      "E8",
      "E9",
      "N10",
      "L11",
      "S13",
      "S14",
      "R15",
      "S15",
      "D16",
      "J16",
      "R16",
      "S16",
      "R17",
      "T17",
      "S18",
      "S19"
    ]
  },
  "targets": {
    "policy_target": "M10"
  },
  "semantic_description": {
    "global_tags": [
      "中盘激战",
      "边空争夺",
      "白棋厚势",
      "黑棋渗透"
    ],
    "strategic_focus": [
      "右上角攻防",
      "中腹潜力",
      "T17附近劫争雏形"
    ],
    "global_summary_cn": "第66手，黑方即将落子，局面处于中盘关键阶段。右上角（T16–S19）形成密集接触战，白棋占据S15、R17、T17等要点构筑厚壁，黑棋Q16、Q17、T18等子试图侵消；中腹尚空旷，M10为政策目标点，暗示潜在打入或分投意图；左下与中腹黑棋孤子（如K2、C3）尚未安定，白棋F3、K3一带有压迫可能。",
    "phase_explanation": "当前为中盘中后期，双方在右上形成局部多回合缠斗，全局未见明显大龙生死，但厚薄与实地平衡微妙，下一着M10若成立将动摇白棋中腹根基。"
  },
  "regions": [
    {
      "region_id": "top_left",
      "summary": "左上角空旷，仅黑K2、C3、B4、B5、B6、C6、D7及白C5、C7、C8零星分布，无激烈接触，属待开发区域。",
      "shapes": [],
      "local_tags": [
        "空旷",
        "低密度",
        "潜在拆二"
      ],
      "key_points": [
        "C3",
        "B4",
        "C5",
        "C7"
      ],
      "group_status": [
        "黑棋低位小块",
        "白棋单关守角"
      ]
    },
    {
      "region_id": "top_center",
      "summary": "上边中段（J3–R3）黑J3、Q3与白F3、K3、L3、M3、N3对峙，黑K4/K5/K6/L6/M6/N6成横向厚势，白L4/N4/L5/M5/O5呼应，呈‘黑白双厚’对顶格局。",
      "shapes": [
        "line"
      ],
      "local_tags": [
        "双厚对峙",
        "横向势力",
        "边路定式延伸"
      ],
      "key_points": [
        "J3",
        "K3",
        "K4",
        "K5",
        "K6",
        "L6",
        "M6",
        "N6",
        "O4",
        "P4"
      ],
      "group_status": [
        "黑棋连片厚势",
        "白棋弹性阵型"
      ]
    },
    {
      "region_id": "top_right",
      "summary": "右上角高度密集：黑Q15/Q16/T16/Q17/Q18/R18/T18与白R15/S15/R16/S16/R17/T17/S18/S19反复交错，已形成近10手连续接触战，T17为最新白棋落点，黑方亟需应对。",
      "shapes": [
        "cluster"
      ],
      "local_tags": [
        "接触战核心区",
        "劫材储备区",
        "边空未定"
      ],
      "key_points": [
        "Q15",
        "Q16",
        "T16",
        "Q17",
        "T18",
        "R18",
        "S15",
        "R17",
        "T17",
        "S18"
      ],
      "group_status": [
        "黑棋攻击性连接",
        "白棋厚壁围空"
      ]
    },
    {
      "region_id": "middle_left",
      "summary": "左中腹（D4–E9）黑D7/F8与白D4/D6/E6/C7/C8/E8/E9构成斜向纠缠，白棋C5–E9呈‘伞形’封锁，黑F8略显孤立，存在被搜根风险。",
      "shapes": [
        "diagonal"
      ],
      "local_tags": [
        "搜根征兆",
        "白棋封锁网",
        "黑棋轻灵试探"
      ],
      "key_points": [
        "D4",
        "D6",
        "E6",
        "F8",
        "E8",
        "E9",
        "C7",
        "C8"
      ],
      "group_status": [
        "白棋联络良好",
        "黑棋F8待援"
      ]
    },
    {
      "region_id": "center",
      "summary": "中央（F10–N12）近乎空白，仅白N10、L11与黑R12/S12/R13/R14零星存在，M10为政策目标点，是黑方最可能的打入/分投位，亦为全局战略枢纽。",
      "shapes": [],
      "local_tags": [
        "战略真空",
        "政策焦点",
        "潜在打入点"
      ],
      "key_points": [
        "M10",
        "N10",
        "L11",
        "R12",
        "S12"
      ],
      "group_status": [
        "无成形势力",
        "未控中枢"
      ]
    },
    {
      "region_id": "middle_right",
      "summary": "右中腹（O12–T14）黑R12/S12/R13/R14与白S13/S14形成小规模对峙，黑四子呈‘直立梯形’，白双子居高临下，但尚未构成有效压迫。",
      "shapes": [
        "ladder_shape"
      ],
      "local_tags": [
        "局部对峙",
        "黑棋扩张中",
        "白棋呼应不足"
      ],
      "key_points": [
        "R12",
        "S12",
        "R13",
        "R14",
        "S13",
        "S14"
      ],
      "group_status": [
        "黑棋成形中",
        "白棋散兵"
      ]
    },
    {
      "region_id": "bottom_left",
      "summary": "左下角（A1–H2）黑K2、C3与白P2、F3等远离主战场，仅黑B4/B5/B6/C6/D7与白C5/D4/D6/E6构成低段牵制，无直接冲突，属次要静默区。",
      "shapes": [],
      "local_tags": [
        "静默区",
        "低位布局余韵",
        "无急所"
      ],
      "key_points": [
        "B4",
        "B5",
        "B6",
        "C6",
        "D7",
        "C5",
        "D4",
        "D6"
      ],
      "group_status": [
        "黑棋低位根基",
        "白棋浅消"
      ]
    },
    {
      "region_id": "bottom_center",
      "summary": "下边中段（G1–Q1）除黑O4/P4/R4与白P2外几无子力，黑R4–P4–O4呈横向小飞守角雏形，白P2孤立，整体空旷且缺乏战略张力。",
      "shapes": [
        "line"
      ],
      "local_tags": [
        "空旷边线",
        "守角未完成",
        "低关注度"
      ],
      "key_points": [
        "O4",
        "P4",
        "R4",
        "P2"
      ],
      "group_status": [
        "黑棋松散守角",
        "白棋单子无援"
      ]
    },
    {
      "region_id": "bottom_right",
      "summary": "右下角（R1–T3）黑Q3/R4与白P2/O4/N4等错落分布，黑Q3尖冲后未深入，白N3/M3/L3/K3已向上延展，此区实际已融入右上主战场，当前属过渡缓冲带。",
      "shapes": [],
      "local_tags": [
        "过渡带",
        "主战场延伸",
        "低密度衔接"
      ],
      "key_points": [
        "Q3",
        "R4",
        "P2",
        "O4",
        "N4"
      ],
      "group_status": [
        "黑棋试探终止",
        "白棋向上转进"
      ]
    }
  ]
}