{
  "meta": {
    "sample_id": "game_2025-06-01a_move_042",
    "game_name": "2025-06-01a",
    "event": "73rd NHK Cup",
    "date": "2025-06-01",
    "black_player": "Son Makoto",
    "white_player": "Ueno Asami"
  },
  "rules": {
    "board_size": 19,
    "komi": 6.5,
    "result": "B+0.5"
  },
  "state": {
    "move_number": 42,
    "to_play": 1,
    "last_move": {
      "color": 0,
      "point": "Q5"
    },
    "recent_moves": [
      {
        "color": 1,
        "point": "N3"
      },
      {
        "color": 0,
        "point": "Q4"
      },
      {
        "color": 1,
        "point": "P4"
      },
      {
        "color": 0,
        "point": "R3"
      },
      {
        "color": 1,
        "point": "R4"
      },
      {
        "color": 0,
        "point": "Q5"
      }
    ],
    "black_stones": [
      "N3",
      "Q3",
      "P4",
      "R4",
      "R6",
      "D10",
      "C11",
      "D11",
      "D13",
      "E14",
      "F14",
      "B15",
      "C15",
      "D15",
      "E16",
      "Q16",
      "R16",
      "M17",
      "N17",
      "O17",
      "P17"
    ],
    "white_stones": [
      "R3",
      "D4",
      "L4",
      "Q4",
      "Q5",
      "C6",
      "C9",
      "C10",
      "C13",
      "E15",
      "F15",
      "G15",
      "H15",
      "B16",
      "D16",
      "D17",
      "Q17",
      "R17",
      "N18",
      "O18",
      "P18"
    ]
  },
  "targets": {
    "policy_target": "R5"
  },
  "semantic_description": {
    "global_tags": [
      "中盘激战",
      "边角缠斗",
      "白棋厚势",
      "黑棋渗透"
    ],
    "strategic_focus": [
      "右下角攻防",
      "中腹潜力争夺",
      "Q5附近对杀未定"
    ],
    "global_summary_cn": "第42手，黑方行棋，局面处于中盘激烈对抗阶段。右下角（Q3–R6）形成复杂接触战，黑白多子交错；左上与中腹黑棋大龙初具规模但尚未安定；白棋在D4、C6–C13一线构筑厚壁，意图借势围空或攻击。全局无明显死活定式，胜负关键在于R5一子的打入效果。",
    "phase_explanation": "中盘阶段，双方在多个局部展开同步作战，尚未进入官子收束，战略重心偏向实地与外势的动态平衡。"
  },
  "regions": [
    {
      "region_id": "top_left",
      "summary": "左上角黑棋C15–B15–C11–D10构成小堡垒，白棋C9–C10–C13施加压力，黑棋尚有D11接应，暂属平稳对峙。",
      "shapes": [
        "corner_enclosure"
      ],
      "local_tags": [
        "黑小堡垒",
        "白压边"
      ],
      "key_points": [
        "C11",
        "C15",
        "C9"
      ],
      "group_status": [
        "black_alive",
        "white_thick"
      ]
    },
    {
      "region_id": "top_center",
      "summary": "上边中段黑棋M17–P17连成厚势，白棋Q17–R17–D17呼应，但黑棋O17–N17–P17具弹性，白棋N18–O18–P18为补强，整体呈对称厚势对峙。",
      "shapes": [
        "side_wall"
      ],
      "local_tags": [
        "黑厚势",
        "白厚势",
        "对称布局"
      ],
      "key_points": [
        "M17",
        "P17",
        "Q17",
        "R17"
      ],
      "group_status": [
        "both_thick"
      ]
    },
    {
      "region_id": "top_right",
      "summary": "右上角黑Q16–R16与白B16–D16–Q17形成高低配合，但无直接接触，属战略呼应区，目前平静。",
      "shapes": [
        "loose_influence"
      ],
      "local_tags": [
        "黑高位",
        "白低位呼应"
      ],
      "key_points": [
        "Q16",
        "R16",
        "B16"
      ],
      "group_status": [
        "neutral"
      ]
    },
    {
      "region_id": "middle_left",
      "summary": "左侧中腹黑E14–F14–E16与白E15–F15–G15–H15形成横向对峙带，黑棋稍显单薄，白棋厚实连贯，黑需防断点。",
      "shapes": [
        "horizontal_line"
      ],
      "local_tags": [
        "黑白对峙带",
        "白厚势压迫"
      ],
      "key_points": [
        "E14",
        "F15",
        "E16"
      ],
      "group_status": [
        "black_weak",
        "white_thick"
      ]
    },
    {
      "region_id": "center",
      "summary": "中央空旷，仅黑D13、E14、F14与白C13、E15等零星分布，是未来势力扩张与打入焦点，当前无成形形状。",
      "shapes": [],
      "local_tags": [
        "中央真空",
        "潜在打入点"
      ],
      "key_points": [
        "D13",
        "E15"
      ],
      "group_status": [
        "unsettled"
      ]
    },
    {
      "region_id": "middle_right",
      "summary": "右中腹黑R6与白Q5–Q4–R4–R3–P4–N3构成密集混战区，已形成‘七子扭杀’雏形，R5为双方必争之眼位/破眼点。",
      "shapes": [
        "fighting_cluster",
        "eye_space_contest"
      ],
      "local_tags": [
        "右下角激战",
        "R5生死点",
        "多子纠缠"
      ],
      "key_points": [
        "R5",
        "Q5",
        "P4",
        "R3"
      ],
      "group_status": [
        "unclear_life_death"
      ]
    },
    {
      "region_id": "bottom_left",
      "summary": "左下角空旷，仅有白D4孤子，黑无应手，属待开发区域，白D4具引征与拆二双重意味。",
      "shapes": [
        "isolated_stone"
      ],
      "local_tags": [
        "白孤子",
        "引征伏笔"
      ],
      "key_points": [
        "D4"
      ],
      "group_status": [
        "white_isolated"
      ]
    },
    {
      "region_id": "bottom_center",
      "summary": "下边中腹空旷，黑无子，白L4为唯一存在，位置偏高，暂无实质影响，属战略缓冲带。",
      "shapes": [
        "single_stone"
      ],
      "local_tags": [
        "白单子",
        "低效占点"
      ],
      "key_points": [
        "L4"
      ],
      "group_status": [
        "white_ineffective"
      ]
    },
    {
      "region_id": "bottom_right",
      "summary": "右下角核心战场：黑N3–Q3–R4–R6 vs 白R3–Q4–Q5–P4，已形成典型‘刀把五’变体结构，R5为唯一未落子交叉点，关系双方眼位存亡。",
      "shapes": [
        "knife_five_variant",
        "life_death_critical"
      ],
      "local_tags": [
        "刀把五变体",
        "R5天王山",
        "对杀前沿"
      ],
      "key_points": [
        "R5",
        "Q5",
        "R4",
        "N3"
      ],
      "group_status": [
        "critical_fight"
      ]
    }
  ]
}